[
  {
    "id": 1,
    "english": "rich",
    "translation": "богатый",
    "translation_ru": "богатый",
    "transcription": "/rɪtʃ/",
    "level": "A2",
    "topic": "basic adjectives",
    "part_of_speech": "adjective",
    "example_en": "He is rich.",
    "example_ru": "Он богатый."
  },
  {
    "id": 2,
    "english": "poor",
    "translation": "бедный",
    "translation_ru": "бедный",
    "transcription": "/pɔːr/",
    "level": "A2",
    "topic": "basic adjectives",
    "part_of_speech": "adjective",
    "example_en": "They are poor.",
    "example_ru": "Они бедные."
  },
  {
    "id": 3,
    "english": "happy",
    "translation": "счастливый",
    "translation_ru": "счастливый",
    "transcription": "/ˈhæpi/",
    "level": "A1",
    "topic": "basic adjectives",
    "part_of_speech": "adjective",
    "example_en": "She is happy today.",
    "example_ru": "Она сегодня счастлива."
  },
  {
    "id": 4,
    "english": "sad",
    "translation": "грустный",
    "translation_ru": "грустный",
    "transcription": "/sæd/",
    "level": "A1",
    "topic": "basic adjectives",
    "part_of_speech": "adjective",
    "example_en": "He looks sad.",
    "example_ru": "Он выглядит грустным."
  },
  {
    "id": 5,
    "english": "angry",
    "translation": "злой",
    "translation_ru": "злой",
    "transcription": "/ˈæŋɡri/",
    "level": "A1",
    "topic": "basic adjectives",
    "part_of_speech": "adjective",
    "example_en": "My brother is angry.",
    "example_ru": "Мой брат злится."
  },
  {
    "id": 6,
    "english": "tired",
    "translation": "уставший",
    "translation_ru": "уставший",
    "transcription": "/ˈtaɪəd/",
    "level": "A1",
    "topic": "basic adjectives",
    "part_of_speech": "adjective",
    "example_en": "I am tired after work.",
    "example_ru": "Я устал после работы."
  },
  {
    "id": 7,
    "english": "hungry",
    "translation": "голодный",
    "translation_ru": "голодный",
    "transcription": "/ˈhʌŋɡri/",
    "level": "A1",
    "topic": "basic adjectives",
    "part_of_speech": "adjective",
    "example_en": "We are hungry.",
    "example_ru": "Мы голодны."
  },
  {
    "id": 8,
    "english": "thirsty",
    "translation": "испытывающий жажду",
    "translation_ru": "испытывающий жажду",
    "transcription": "/ˈθɜːsti/",
    "level": "A1",
    "topic": "basic adjectives",
    "part_of_speech": "adjective",
    "example_en": "I am thirsty.",
    "example_ru": "Я хочу пить."
  },
  {
    "id": 9,
    "english": "busy",
    "translation": "занятый",
    "translation_ru": "занятый",
    "transcription": "/ˈbɪzi/",
    "level": "A1",
    "topic": "basic adjectives",
    "part_of_speech": "adjective",
    "example_en": "She is busy now.",
    "example_ru": "Она сейчас занята."
  },
  {
    "id": 10,
    "english": "free",
    "translation": "свободный",
    "translation_ru": "свободный",
    "transcription": "/friː/",
    "level": "A1",
    "topic": "basic adjectives",
    "part_of_speech": "adjective",
    "example_en": "Are you free tonight?",
    "example_ru": "Ты свободен сегодня вечером?"
  },
  {
    "id": 11,
    "english": "early",
    "translation": "ранний",
    "translation_ru": "ранний",
    "transcription": "/ˈɜːli/",
    "level": "A1",
    "topic": "basic adjectives",
    "part_of_speech": "adjective",
    "example_en": "We arrived early.",
    "example_ru": "Мы приехали рано."
  },
  {
    "id": 12,
    "english": "late",
    "translation": "поздний",
    "translation_ru": "поздний",
    "transcription": "/leɪt/",
    "level": "A1",
    "topic": "basic adjectives",
    "part_of_speech": "adjective",
    "example_en": "The train is late.",
    "example_ru": "Поезд опаздывает."
  },
  {
    "id": 13,
    "english": "clean",
    "translation": "чистый",
    "translation_ru": "чистый",
    "transcription": "/kliːn/",
    "level": "A1",
    "topic": "basic adjectives",
    "part_of_speech": "adjective",
    "example_en": "The room is clean.",
    "example_ru": "Комната чистая."
  },
  {
    "id": 14,
    "english": "dirty",
    "translation": "грязный",
    "translation_ru": "грязный",
    "transcription": "/ˈdɜːti/",
    "level": "A1",
    "topic": "basic adjectives",
    "part_of_speech": "adjective",
    "example_en": "Your shoes are dirty.",
    "example_ru": "Твои ботинки грязные."
  },
  {
    "id": 15,
    "english": "cheap",
    "translation": "дешёвый",
    "translation_ru": "дешёвый",
    "transcription": "/tʃiːp/",
    "level": "A1",
    "topic": "basic adjectives",
    "part_of_speech": "adjective",
    "example_en": "This bag is cheap.",
    "example_ru": "Эта сумка дешёвая."
  },
  {
    "id": 16,
    "english": "expensive",
    "translation": "дорогой",
    "translation_ru": "дорогой",
    "transcription": "/ɪkˈspensɪv/",
    "level": "A1",
    "topic": "basic adjectives",
    "part_of_speech": "adjective",
    "example_en": "This phone is expensive.",
    "example_ru": "Этот телефон дорогой."
  },
  {
    "id": 17,
    "english": "strong",
    "translation": "сильный",
    "translation_ru": "сильный",
    "transcription": "/strɒŋ/",
    "level": "A1",
    "topic": "basic adjectives",
    "part_of_speech": "adjective",
    "example_en": "He is strong.",
    "example_ru": "Он сильный."
  },
  {
    "id": 18,
    "english": "weak",
    "translation": "слабый",
    "translation_ru": "слабый",
    "transcription": "/wiːk/",
    "level": "A2",
    "topic": "basic adjectives",
    "part_of_speech": "adjective",
    "example_en": "The signal is weak.",
    "example_ru": "Сигнал слабый."
  },
  {
    "id": 19,
    "english": "quiet",
    "translation": "тихий",
    "translation_ru": "тихий",
    "transcription": "/ˈkwaɪət/",
    "level": "A1",
    "topic": "basic adjectives",
    "part_of_speech": "adjective",
    "example_en": "The street is quiet.",
    "example_ru": "Улица тихая."
  },
  {
    "id": 20,
    "english": "loud",
    "translation": "громкий",
    "translation_ru": "громкий",
    "transcription": "/laʊd/",
    "level": "A2",
    "topic": "basic adjectives",
    "part_of_speech": "adjective",
    "example_en": "The music is loud.",
    "example_ru": "Музыка громкая."
  },
  {
    "id": 21,
    "english": "goat",
    "translation": "коза",
    "translation_ru": "коза",
    "transcription": "/ɡəʊt/",
    "level": "A1",
    "topic": "animals",
    "part_of_speech": "noun",
    "example_en": "The goat is eating grass.",
    "example_ru": "Коза ест траву."
  },
  {
    "id": 22,
    "english": "cow",
    "translation": "корова",
    "translation_ru": "корова",
    "transcription": "/kaʊ/",
    "level": "A1",
    "topic": "animals",
    "part_of_speech": "noun",
    "example_en": "The cow gives milk.",
    "example_ru": "Корова даёт молоко."
  },
  {
    "id": 23,
    "english": "horse",
    "translation": "лошадь",
    "translation_ru": "лошадь",
    "transcription": "/hɔːs/",
    "level": "A1",
    "topic": "animals",
    "part_of_speech": "noun",
    "example_en": "The horse runs fast.",
    "example_ru": "Лошадь быстро бежит."
  },
  {
    "id": 24,
    "english": "sheep",
    "translation": "овца",
    "translation_ru": "овца",
    "transcription": "/ʃiːp/",
    "level": "A1",
    "topic": "animals",
    "part_of_speech": "noun",
    "example_en": "The sheep is in the field.",
    "example_ru": "Овца в поле."
  },
  {
    "id": 25,
    "english": "pig",
    "translation": "свинья",
    "translation_ru": "свинья",
    "transcription": "/pɪɡ/",
    "level": "A1",
    "topic": "animals",
    "part_of_speech": "noun",
    "example_en": "The pig is sleeping.",
    "example_ru": "Свинья спит."
  },
  {
    "id": 26,
    "english": "chicken",
    "translation": "курица",
    "translation_ru": "курица",
    "transcription": "/ˈtʃɪkɪn/",
    "level": "A1",
    "topic": "animals",
    "part_of_speech": "noun",
    "example_en": "The chicken is in the garden.",
    "example_ru": "Курица в саду."
  },
  {
    "id": 27,
    "english": "duck",
    "translation": "утка",
    "translation_ru": "утка",
    "transcription": "/dʌk/",
    "level": "A1",
    "topic": "animals",
    "part_of_speech": "noun",
    "example_en": "The duck is swimming.",
    "example_ru": "Утка плавает."
  },
  {
    "id": 28,
    "english": "rabbit",
    "translation": "кролик",
    "translation_ru": "кролик",
    "transcription": "/ˈræbɪt/",
    "level": "A1",
    "topic": "animals",
    "part_of_speech": "noun",
    "example_en": "The rabbit has long ears.",
    "example_ru": "У кролика длинные уши."
  },
  {
    "id": 29,
    "english": "mouse",
    "translation": "мышь",
    "translation_ru": "мышь",
    "transcription": "/maʊs/",
    "level": "A1",
    "topic": "animals",
    "part_of_speech": "noun",
    "example_en": "A mouse is under the table.",
    "example_ru": "Мышь под столом."
  },
  {
    "id": 30,
    "english": "snake",
    "translation": "змея",
    "translation_ru": "змея",
    "transcription": "/sneɪk/",
    "level": "A2",
    "topic": "animals",
    "part_of_speech": "noun",
    "example_en": "I saw a snake in the grass.",
    "example_ru": "Я увидел змею в траве."
  },
  {
    "id": 31,
    "english": "bear",
    "translation": "медведь",
    "translation_ru": "медведь",
    "transcription": "/beər/",
    "level": "A1",
    "topic": "animals",
    "part_of_speech": "noun",
    "example_en": "A bear lives in the forest.",
    "example_ru": "Медведь живёт в лесу."
  },
  {
    "id": 32,
    "english": "wolf",
    "translation": "волк",
    "translation_ru": "волк",
    "transcription": "/wʊlf/",
    "level": "A2",
    "topic": "animals",
    "part_of_speech": "noun",
    "example_en": "A wolf is a wild animal.",
    "example_ru": "Волк — дикое животное."
  },
  {
    "id": 33,
    "english": "fox",
    "translation": "лиса",
    "translation_ru": "лиса",
    "transcription": "/fɒks/",
    "level": "A2",
    "topic": "animals",
    "part_of_speech": "noun",
    "example_en": "The fox is near the tree.",
    "example_ru": "Лиса возле дерева."
  },
  {
    "id": 34,
    "english": "lion",
    "translation": "лев",
    "translation_ru": "лев",
    "transcription": "/ˈlaɪən/",
    "level": "A1",
    "topic": "animals",
    "part_of_speech": "noun",
    "example_en": "A lion is a strong animal.",
    "example_ru": "Лев — сильное животное."
  },
  {
    "id": 35,
    "english": "tiger",
    "translation": "тигр",
    "translation_ru": "тигр",
    "transcription": "/ˈtaɪɡər/",
    "level": "A1",
    "topic": "animals",
    "part_of_speech": "noun",
    "example_en": "The tiger is sleeping.",
    "example_ru": "Тигр спит."
  },
  {
    "id": 36,
    "english": "elephant",
    "translation": "слон",
    "translation_ru": "слон",
    "transcription": "/ˈelɪfənt/",
    "level": "A1",
    "topic": "animals",
    "part_of_speech": "noun",
    "example_en": "The elephant is very big.",
    "example_ru": "Слон очень большой."
  },
  {
    "id": 37,
    "english": "monkey",
    "translation": "обезьяна",
    "translation_ru": "обезьяна",
    "transcription": "/ˈmʌŋki/",
    "level": "A1",
    "topic": "animals",
    "part_of_speech": "noun",
    "example_en": "The monkey is in the tree.",
    "example_ru": "Обезьяна на дереве."
  },
  {
    "id": 38,
    "english": "bird",
    "translation": "птица",
    "translation_ru": "птица",
    "transcription": "/bɜːd/",
    "level": "A1",
    "topic": "animals",
    "part_of_speech": "noun",
    "example_en": "A bird is singing.",
    "example_ru": "Птица поёт."
  },
  {
    "id": 39,
    "english": "fish",
    "translation": "рыба",
    "translation_ru": "рыба",
    "transcription": "/fɪʃ/",
    "level": "A1",
    "topic": "animals",
    "part_of_speech": "noun",
    "example_en": "The fish is in the river.",
    "example_ru": "Рыба в реке."
  },
  {
    "id": 40,
    "english": "insect",
    "translation": "насекомое",
    "translation_ru": "насекомое",
    "transcription": "/ˈɪnsekt/",
    "level": "A2",
    "topic": "animals",
    "part_of_speech": "noun",
    "example_en": "An insect is on the wall.",
    "example_ru": "Насекомое на стене."
  },
  {
    "id": 41,
    "english": "bread",
    "translation": "хлеб",
    "translation_ru": "хлеб",
    "transcription": "/bred/",
    "level": "A1",
    "topic": "food",
    "part_of_speech": "noun",
    "example_en": "I bought fresh bread.",
    "example_ru": "Я купил свежий хлеб."
  },
  {
    "id": 42,
    "english": "butter",
    "translation": "масло",
    "translation_ru": "масло",
    "transcription": "/ˈbʌtər/",
    "level": "A1",
    "topic": "food",
    "part_of_speech": "noun",
    "example_en": "Put some butter on the bread.",
    "example_ru": "Положи немного масла на хлеб."
  },
  {
    "id": 43,
    "english": "cheese",
    "translation": "сыр",
    "translation_ru": "сыр",
    "transcription": "/tʃiːz/",
    "level": "A1",
    "topic": "food",
    "part_of_speech": "noun",
    "example_en": "I like cheese.",
    "example_ru": "Мне нравится сыр."
  },
  {
    "id": 44,
    "english": "egg",
    "translation": "яйцо",
    "translation_ru": "яйцо",
    "transcription": "/eɡ/",
    "level": "A1",
    "topic": "food",
    "part_of_speech": "noun",
    "example_en": "She boiled an egg.",
    "example_ru": "Она сварила яйцо."
  },
  {
    "id": 45,
    "english": "meat",
    "translation": "мясо",
    "translation_ru": "мясо",
    "transcription": "/miːt/",
    "level": "A1",
    "topic": "food",
    "part_of_speech": "noun",
    "example_en": "He doesn't eat meat.",
    "example_ru": "Он не ест мясо."
  },
  {
    "id": 46,
    "english": "rice",
    "translation": "рис",
    "translation_ru": "рис",
    "transcription": "/raɪs/",
    "level": "A1",
    "topic": "food",
    "part_of_speech": "noun",
    "example_en": "We had rice for dinner.",
    "example_ru": "Мы ели рис на ужин."
  },
  {
    "id": 47,
    "english": "soup",
    "translation": "суп",
    "translation_ru": "суп",
    "transcription": "/suːp/",
    "level": "A1",
    "topic": "food",
    "part_of_speech": "noun",
    "example_en": "The soup is hot.",
    "example_ru": "Суп горячий."
  },
  {
    "id": 48,
    "english": "salad",
    "translation": "салат",
    "translation_ru": "салат",
    "transcription": "/ˈsæləd/",
    "level": "A1",
    "topic": "food",
    "part_of_speech": "noun",
    "example_en": "I made a salad.",
    "example_ru": "Я сделал салат."
  },
  {
    "id": 49,
    "english": "apple",
    "translation": "яблоко",
    "translation_ru": "яблоко",
    "transcription": "/ˈæpl/",
    "level": "A1",
    "topic": "food",
    "part_of_speech": "noun",
    "example_en": "She ate an apple.",
    "example_ru": "Она съела яблоко."
  },
  {
    "id": 50,
    "english": "banana",
    "translation": "банан",
    "translation_ru": "банан",
    "transcription": "/bəˈnɑːnə/",
    "level": "A1",
    "topic": "food",
    "part_of_speech": "noun",
    "example_en": "He bought bananas.",
    "example_ru": "Он купил бананы."
  },
  {
    "id": 51,
    "english": "orange",
    "translation": "апельсин",
    "translation_ru": "апельсин",
    "transcription": "/ˈɒrɪndʒ/",
    "level": "A1",
    "topic": "food",
    "part_of_speech": "noun",
    "example_en": "Would you like an orange?",
    "example_ru": "Хочешь апельсин?"
  },
  {
    "id": 52,
    "english": "potato",
    "translation": "картофель",
    "translation_ru": "картофель",
    "transcription": "/pəˈteɪtəʊ/",
    "level": "A1",
    "topic": "food",
    "part_of_speech": "noun",
    "example_en": "I cooked potatoes.",
    "example_ru": "Я приготовил картофель."
  },
  {
    "id": 53,
    "english": "tomato",
    "translation": "помидор",
    "translation_ru": "помидор",
    "transcription": "/təˈmɑːtəʊ/",
    "level": "A1",
    "topic": "food",
    "part_of_speech": "noun",
    "example_en": "Put a tomato in the salad.",
    "example_ru": "Положи помидор в салат."
  },
  {
    "id": 54,
    "english": "onion",
    "translation": "лук",
    "translation_ru": "лук",
    "transcription": "/ˈʌnjən/",
    "level": "A2",
    "topic": "food",
    "part_of_speech": "noun",
    "example_en": "Cut the onion carefully.",
    "example_ru": "Аккуратно нарежь лук."
  },
  {
    "id": 55,
    "english": "salt",
    "translation": "соль",
    "translation_ru": "соль",
    "transcription": "/sɔːlt/",
    "level": "A1",
    "topic": "food",
    "part_of_speech": "noun",
    "example_en": "Add a little salt.",
    "example_ru": "Добавь немного соли."
  },
  {
    "id": 56,
    "english": "sugar",
    "translation": "сахар",
    "translation_ru": "сахар",
    "transcription": "/ˈʃʊɡər/",
    "level": "A1",
    "topic": "food",
    "part_of_speech": "noun",
    "example_en": "I don't take sugar in tea.",
    "example_ru": "Я не кладу сахар в чай."
  },
  {
    "id": 57,
    "english": "tea",
    "translation": "чай",
    "translation_ru": "чай",
    "transcription": "/tiː/",
    "level": "A1",
    "topic": "food",
    "part_of_speech": "noun",
    "example_en": "I drink tea every morning.",
    "example_ru": "Я пью чай каждое утро."
  },
  {
    "id": 58,
    "english": "coffee",
    "translation": "кофе",
    "translation_ru": "кофе",
    "transcription": "/ˈkɒfi/",
    "level": "A1",
    "topic": "food",
    "part_of_speech": "noun",
    "example_en": "She drinks coffee at work.",
    "example_ru": "Она пьёт кофе на работе."
  },
  {
    "id": 59,
    "english": "juice",
    "translation": "сок",
    "translation_ru": "сок",
    "transcription": "/dʒuːs/",
    "level": "A1",
    "topic": "food",
    "part_of_speech": "noun",
    "example_en": "The juice is cold.",
    "example_ru": "Сок холодный."
  },
  {
    "id": 60,
    "english": "water",
    "translation": "вода",
    "translation_ru": "вода",
    "transcription": "/ˈwɔːtər/",
    "level": "A1",
    "topic": "food",
    "part_of_speech": "noun",
    "example_en": "Drink more water.",
    "example_ru": "Пей больше воды."
  },
  {
    "id": 61,
    "english": "house",
    "translation": "дом",
    "translation_ru": "дом",
    "transcription": "/haʊs/",
    "level": "A1",
    "topic": "home",
    "part_of_speech": "noun",
    "example_en": "Their house is big.",
    "example_ru": "Их дом большой."
  },
  {
    "id": 62,
    "english": "flat",
    "translation": "квартира",
    "translation_ru": "квартира",
    "transcription": "/flæt/",
    "level": "A1",
    "topic": "home",
    "part_of_speech": "noun",
    "example_en": "I live in a small flat.",
    "example_ru": "Я живу в маленькой квартире."
  },
  {
    "id": 63,
    "english": "room",
    "translation": "комната",
    "translation_ru": "комната",
    "transcription": "/ruːm/",
    "level": "A1",
    "topic": "home",
    "part_of_speech": "noun",
    "example_en": "My room is clean.",
    "example_ru": "Моя комната чистая."
  },
  {
    "id": 64,
    "english": "kitchen",
    "translation": "кухня",
    "translation_ru": "кухня",
    "transcription": "/ˈkɪtʃɪn/",
    "level": "A1",
    "topic": "home",
    "part_of_speech": "noun",
    "example_en": "She is in the kitchen.",
    "example_ru": "Она на кухне."
  },
  {
    "id": 65,
    "english": "bathroom",
    "translation": "ванная",
    "translation_ru": "ванная",
    "transcription": "/ˈbɑːθruːm/",
    "level": "A1",
    "topic": "home",
    "part_of_speech": "noun",
    "example_en": "The bathroom is upstairs.",
    "example_ru": "Ванная наверху."
  },
  {
    "id": 66,
    "english": "bedroom",
    "translation": "спальня",
    "translation_ru": "спальня",
    "transcription": "/ˈbedruːm/",
    "level": "A1",
    "topic": "home",
    "part_of_speech": "noun",
    "example_en": "My bedroom is small.",
    "example_ru": "Моя спальня маленькая."
  },
  {
    "id": 67,
    "english": "door",
    "translation": "дверь",
    "translation_ru": "дверь",
    "transcription": "/dɔːr/",
    "level": "A1",
    "topic": "home",
    "part_of_speech": "noun",
    "example_en": "Close the door, please.",
    "example_ru": "Закрой дверь, пожалуйста."
  },
  {
    "id": 68,
    "english": "window",
    "translation": "окно",
    "translation_ru": "окно",
    "transcription": "/ˈwɪndəʊ/",
    "level": "A1",
    "topic": "home",
    "part_of_speech": "noun",
    "example_en": "Open the window.",
    "example_ru": "Открой окно."
  },
  {
    "id": 69,
    "english": "wall",
    "translation": "стена",
    "translation_ru": "стена",
    "transcription": "/wɔːl/",
    "level": "A1",
    "topic": "home",
    "part_of_speech": "noun",
    "example_en": "There is a picture on the wall.",
    "example_ru": "На стене висит картина."
  },
  {
    "id": 70,
    "english": "floor",
    "translation": "пол",
    "translation_ru": "пол",
    "transcription": "/flɔːr/",
    "level": "A1",
    "topic": "home",
    "part_of_speech": "noun",
    "example_en": "The floor is dirty.",
    "example_ru": "Пол грязный."
  },
  {
    "id": 71,
    "english": "ceiling",
    "translation": "потолок",
    "translation_ru": "потолок",
    "transcription": "/ˈsiːlɪŋ/",
    "level": "A2",
    "topic": "home",
    "part_of_speech": "noun",
    "example_en": "The ceiling is white.",
    "example_ru": "Потолок белый."
  },
  {
    "id": 72,
    "english": "table",
    "translation": "стол",
    "translation_ru": "стол",
    "transcription": "/ˈteɪbl/",
    "level": "A1",
    "topic": "home",
    "part_of_speech": "noun",
    "example_en": "The keys are on the table.",
    "example_ru": "Ключи на столе."
  },
  {
    "id": 73,
    "english": "chair",
    "translation": "стул",
    "translation_ru": "стул",
    "transcription": "/tʃeər/",
    "level": "A1",
    "topic": "home",
    "part_of_speech": "noun",
    "example_en": "Sit on this chair.",
    "example_ru": "Сядь на этот стул."
  },
  {
    "id": 74,
    "english": "bed",
    "translation": "кровать",
    "translation_ru": "кровать",
    "transcription": "/bed/",
    "level": "A1",
    "topic": "home",
    "part_of_speech": "noun",
    "example_en": "The bed is comfortable.",
    "example_ru": "Кровать удобная."
  },
  {
    "id": 75,
    "english": "sofa",
    "translation": "диван",
    "translation_ru": "диван",
    "transcription": "/ˈsəʊfə/",
    "level": "A1",
    "topic": "home",
    "part_of_speech": "noun",
    "example_en": "He is sitting on the sofa.",
    "example_ru": "Он сидит на диване."
  },
  {
    "id": 76,
    "english": "lamp",
    "translation": "лампа",
    "translation_ru": "лампа",
    "transcription": "/læmp/",
    "level": "A1",
    "topic": "home",
    "part_of_speech": "noun",
    "example_en": "Turn on the lamp.",
    "example_ru": "Включи лампу."
  },
  {
    "id": 77,
    "english": "mirror",
    "translation": "зеркало",
    "translation_ru": "зеркало",
    "transcription": "/ˈmɪrər/",
    "level": "A2",
    "topic": "home",
    "part_of_speech": "noun",
    "example_en": "There is a mirror in the hall.",
    "example_ru": "В коридоре есть зеркало."
  },
  {
    "id": 78,
    "english": "carpet",
    "translation": "ковёр",
    "translation_ru": "ковёр",
    "transcription": "/ˈkɑːpɪt/",
    "level": "A2",
    "topic": "home",
    "part_of_speech": "noun",
    "example_en": "The carpet is soft.",
    "example_ru": "Ковёр мягкий."
  },
  {
    "id": 79,
    "english": "fridge",
    "translation": "холодильник",
    "translation_ru": "холодильник",
    "transcription": "/frɪdʒ/",
    "level": "A1",
    "topic": "home",
    "part_of_speech": "noun",
    "example_en": "The milk is in the fridge.",
    "example_ru": "Молоко в холодильнике."
  },
  {
    "id": 80,
    "english": "key",
    "translation": "ключ",
    "translation_ru": "ключ",
    "transcription": "/kiː/",
    "level": "A1",
    "topic": "home",
    "part_of_speech": "noun",
    "example_en": "I lost my key.",
    "example_ru": "Я потерял ключ."
  },
  {
    "id": 81,
    "english": "mother",
    "translation": "мать",
    "translation_ru": "мать",
    "transcription": "/ˈmʌðər/",
    "level": "A1",
    "topic": "family",
    "part_of_speech": "noun",
    "example_en": "My mother is at home.",
    "example_ru": "Моя мама дома."
  },
  {
    "id": 82,
    "english": "father",
    "translation": "отец",
    "translation_ru": "отец",
    "transcription": "/ˈfɑːðər/",
    "level": "A1",
    "topic": "family",
    "part_of_speech": "noun",
    "example_en": "His father works in a bank.",
    "example_ru": "Его отец работает в банке."
  },
  {
    "id": 83,
    "english": "parent",
    "translation": "родитель",
    "translation_ru": "родитель",
    "transcription": "/ˈpeərənt/",
    "level": "A1",
    "topic": "family",
    "part_of_speech": "noun",
    "example_en": "A child needs a parent.",
    "example_ru": "Ребёнку нужен родитель."
  },
  {
    "id": 84,
    "english": "child",
    "translation": "ребёнок",
    "translation_ru": "ребёнок",
    "transcription": "/tʃaɪld/",
    "level": "A1",
    "topic": "family",
    "part_of_speech": "noun",
    "example_en": "The child is sleeping.",
    "example_ru": "Ребёнок спит."
  },
  {
    "id": 85,
    "english": "son",
    "translation": "сын",
    "translation_ru": "сын",
    "transcription": "/sʌn/",
    "level": "A1",
    "topic": "family",
    "part_of_speech": "noun",
    "example_en": "Their son is five.",
    "example_ru": "Их сыну пять лет."
  },
  {
    "id": 86,
    "english": "daughter",
    "translation": "дочь",
    "translation_ru": "дочь",
    "transcription": "/ˈdɔːtər/",
    "level": "A1",
    "topic": "family",
    "part_of_speech": "noun",
    "example_en": "My daughter likes music.",
    "example_ru": "Моя дочь любит музыку."
  },
  {
    "id": 87,
    "english": "brother",
    "translation": "брат",
    "translation_ru": "брат",
    "transcription": "/ˈbrʌðər/",
    "level": "A1",
    "topic": "family",
    "part_of_speech": "noun",
    "example_en": "I have one brother.",
    "example_ru": "У меня есть один брат."
  },
  {
    "id": 88,
    "english": "sister",
    "translation": "сестра",
    "translation_ru": "сестра",
    "transcription": "/ˈsɪstər/",
    "level": "A1",
    "topic": "family",
    "part_of_speech": "noun",
    "example_en": "His sister is a doctor.",
    "example_ru": "Его сестра — врач."
  },
  {
    "id": 89,
    "english": "husband",
    "translation": "муж",
    "translation_ru": "муж",
    "transcription": "/ˈhʌzbənd/",
    "level": "A1",
    "topic": "family",
    "part_of_speech": "noun",
    "example_en": "Her husband is kind.",
    "example_ru": "Её муж добрый."
  },
  {
    "id": 90,
    "english": "wife",
    "translation": "жена",
    "translation_ru": "жена",
    "transcription": "/waɪf/",
    "level": "A1",
    "topic": "family",
    "part_of_speech": "noun",
    "example_en": "His wife is a teacher.",
    "example_ru": "Его жена — учитель."
  },
  {
    "id": 91,
    "english": "grandmother",
    "translation": "бабушка",
    "translation_ru": "бабушка",
    "transcription": "/ˈɡrænmʌðər/",
    "level": "A1",
    "topic": "family",
    "part_of_speech": "noun",
    "example_en": "My grandmother cooks well.",
    "example_ru": "Моя бабушка хорошо готовит."
  },
  {
    "id": 92,
    "english": "grandfather",
    "translation": "дедушка",
    "translation_ru": "дедушка",
    "transcription": "/ˈɡrænfɑːðər/",
    "level": "A1",
    "topic": "family",
    "part_of_speech": "noun",
    "example_en": "My grandfather lives in a village.",
    "example_ru": "Мой дедушка живёт в деревне."
  },
  {
    "id": 93,
    "english": "uncle",
    "translation": "дядя",
    "translation_ru": "дядя",
    "transcription": "/ˈʌŋkl/",
    "level": "A1",
    "topic": "family",
    "part_of_speech": "noun",
    "example_en": "My uncle has a car.",
    "example_ru": "У моего дяди есть машина."
  },
  {
    "id": 94,
    "english": "aunt",
    "translation": "тётя",
    "translation_ru": "тётя",
    "transcription": "/ɑːnt/",
    "level": "A1",
    "topic": "family",
    "part_of_speech": "noun",
    "example_en": "Her aunt lives in London.",
    "example_ru": "Её тётя живёт в Лондоне."
  },
  {
    "id": 95,
    "english": "cousin",
    "translation": "двоюродный брат или сестра",
    "translation_ru": "двоюродный брат или сестра",
    "transcription": "/ˈkʌzn/",
    "level": "A2",
    "topic": "family",
    "part_of_speech": "noun",
    "example_en": "My cousin studies English.",
    "example_ru": "Мой двоюродный брат учит английский."
  },
  {
    "id": 96,
    "english": "relative",
    "translation": "родственник",
    "translation_ru": "родственник",
    "transcription": "/ˈrelətɪv/",
    "level": "A2",
    "topic": "family",
    "part_of_speech": "noun",
    "example_en": "Many relatives came to the party.",
    "example_ru": "На вечеринку пришло много родственников."
  },
  {
    "id": 97,
    "english": "family",
    "translation": "семья",
    "translation_ru": "семья",
    "transcription": "/ˈfæməli/",
    "level": "A1",
    "topic": "family",
    "part_of_speech": "noun",
    "example_en": "My family is small.",
    "example_ru": "Моя семья маленькая."
  },
  {
    "id": 98,
    "english": "baby",
    "translation": "младенец",
    "translation_ru": "младенец",
    "transcription": "/ˈbeɪbi/",
    "level": "A1",
    "topic": "family",
    "part_of_speech": "noun",
    "example_en": "The baby is crying.",
    "example_ru": "Младенец плачет."
  },
  {
    "id": 99,
    "english": "adult",
    "translation": "взрослый",
    "translation_ru": "взрослый",
    "transcription": "/ˈædʌlt/",
    "level": "A2",
    "topic": "family",
    "part_of_speech": "noun",
    "example_en": "This ticket is for an adult.",
    "example_ru": "Этот билет для взрослого."
  },
  {
    "id": 100,
    "english": "teenager",
    "translation": "подросток",
    "translation_ru": "подросток",
    "transcription": "/ˈtiːneɪdʒər/",
    "level": "A2",
    "topic": "family",
    "part_of_speech": "noun",
    "example_en": "The teenager is listening to music.",
    "example_ru": "Подросток слушает музыку."
  },
  {
    "id": 101,
    "english": "wake",
    "translation": "просыпаться",
    "translation_ru": "просыпаться",
    "transcription": "/weɪk/",
    "level": "A1",
    "topic": "daily verbs",
    "part_of_speech": "verb",
    "example_en": "I wake up at seven.",
    "example_ru": "Я просыпаюсь в семь."
  },
  {
    "id": 102,
    "english": "sleep",
    "translation": "спать",
    "translation_ru": "спать",
    "transcription": "/sliːp/",
    "level": "A1",
    "topic": "daily verbs",
    "part_of_speech": "verb",
    "example_en": "I sleep eight hours.",
    "example_ru": "Я сплю восемь часов."
  },
  {
    "id": 103,
    "english": "eat",
    "translation": "есть",
    "translation_ru": "есть",
    "transcription": "/iːt/",
    "level": "A1",
    "topic": "daily verbs",
    "part_of_speech": "verb",
    "example_en": "We eat dinner at home.",
    "example_ru": "Мы ужинаем дома."
  },
  {
    "id": 104,
    "english": "drink",
    "translation": "пить",
    "translation_ru": "пить",
    "transcription": "/drɪŋk/",
    "level": "A1",
    "topic": "daily verbs",
    "part_of_speech": "verb",
    "example_en": "Drink some water.",
    "example_ru": "Выпей немного воды."
  },
  {
    "id": 105,
    "english": "cook",
    "translation": "готовить",
    "translation_ru": "готовить",
    "transcription": "/kʊk/",
    "level": "A1",
    "topic": "daily verbs",
    "part_of_speech": "verb",
    "example_en": "I cook every evening.",
    "example_ru": "Я готовлю каждый вечер."
  },
  {
    "id": 106,
    "english": "wash",
    "translation": "мыть",
    "translation_ru": "мыть",
    "transcription": "/wɒʃ/",
    "level": "A1",
    "topic": "daily verbs",
    "part_of_speech": "verb",
    "example_en": "Wash your hands.",
    "example_ru": "Вымой руки."
  },
  {
    "id": 107,
    "english": "tidy",
    "translation": "убирать",
    "translation_ru": "убирать",
    "transcription": "/ˈtaɪdi/",
    "level": "A1",
    "topic": "daily verbs",
    "part_of_speech": "verb",
    "example_en": "I tidy my room on Saturday.",
    "example_ru": "Я убираю комнату в субботу."
  },
  {
    "id": 108,
    "english": "open",
    "translation": "открывать",
    "translation_ru": "открывать",
    "transcription": "/ˈəʊpən/",
    "level": "A1",
    "topic": "daily verbs",
    "part_of_speech": "verb",
    "example_en": "Open the door, please.",
    "example_ru": "Открой дверь, пожалуйста."
  },
  {
    "id": 109,
    "english": "close",
    "translation": "закрывать",
    "translation_ru": "закрывать",
    "transcription": "/kləʊz/",
    "level": "A1",
    "topic": "daily verbs",
    "part_of_speech": "verb",
    "example_en": "Close the window.",
    "example_ru": "Закрой окно."
  },
  {
    "id": 110,
    "english": "start",
    "translation": "начинать",
    "translation_ru": "начинать",
    "transcription": "/stɑːt/",
    "level": "A1",
    "topic": "daily verbs",
    "part_of_speech": "verb",
    "example_en": "The lesson starts at nine.",
    "example_ru": "Урок начинается в девять."
  },
  {
    "id": 111,
    "english": "finish",
    "translation": "заканчивать",
    "translation_ru": "заканчивать",
    "transcription": "/ˈfɪnɪʃ/",
    "level": "A1",
    "topic": "daily verbs",
    "part_of_speech": "verb",
    "example_en": "I finish work at six.",
    "example_ru": "Я заканчиваю работу в шесть."
  },
  {
    "id": 112,
    "english": "wait",
    "translation": "ждать",
    "translation_ru": "ждать",
    "transcription": "/weɪt/",
    "level": "A1",
    "topic": "daily verbs",
    "part_of_speech": "verb",
    "example_en": "Wait for me here.",
    "example_ru": "Жди меня здесь."
  },
  {
    "id": 113,
    "english": "help",
    "translation": "помогать",
    "translation_ru": "помогать",
    "transcription": "/help/",
    "level": "A1",
    "topic": "daily verbs",
    "part_of_speech": "verb",
    "example_en": "Can you help me?",
    "example_ru": "Ты можешь мне помочь?"
  },
  {
    "id": 114,
    "english": "call",
    "translation": "звонить",
    "translation_ru": "звонить",
    "transcription": "/kɔːl/",
    "level": "A1",
    "topic": "daily verbs",
    "part_of_speech": "verb",
    "example_en": "I will call you later.",
    "example_ru": "Я позвоню тебе позже."
  },
  {
    "id": 115,
    "english": "ask",
    "translation": "спрашивать",
    "translation_ru": "спрашивать",
    "transcription": "/ɑːsk/",
    "level": "A1",
    "topic": "daily verbs",
    "part_of_speech": "verb",
    "example_en": "Ask the teacher a question.",
    "example_ru": "Задай учителю вопрос."
  },
  {
    "id": 116,
    "english": "answer",
    "translation": "отвечать",
    "translation_ru": "отвечать",
    "transcription": "/ˈɑːnsər/",
    "level": "A1",
    "topic": "daily verbs",
    "part_of_speech": "verb",
    "example_en": "Please answer my question.",
    "example_ru": "Пожалуйста, ответь на мой вопрос."
  },
  {
    "id": 117,
    "english": "buy",
    "translation": "покупать",
    "translation_ru": "покупать",
    "transcription": "/baɪ/",
    "level": "A1",
    "topic": "daily verbs",
    "part_of_speech": "verb",
    "example_en": "I need to buy bread.",
    "example_ru": "Мне нужно купить хлеб."
  },
  {
    "id": 118,
    "english": "sell",
    "translation": "продавать",
    "translation_ru": "продавать",
    "transcription": "/sel/",
    "level": "A1",
    "topic": "daily verbs",
    "part_of_speech": "verb",
    "example_en": "They sell fruit here.",
    "example_ru": "Здесь продают фрукты."
  },
  {
    "id": 119,
    "english": "pay",
    "translation": "платить",
    "translation_ru": "платить",
    "transcription": "/peɪ/",
    "level": "A1",
    "topic": "daily verbs",
    "part_of_speech": "verb",
    "example_en": "I'll pay for dinner.",
    "example_ru": "Я заплачу за ужин."
  },
  {
    "id": 120,
    "english": "choose",
    "translation": "выбирать",
    "translation_ru": "выбирать",
    "transcription": "/tʃuːz/",
    "level": "A2",
    "topic": "daily verbs",
    "part_of_speech": "verb",
    "example_en": "Choose the right answer.",
    "example_ru": "Выбери правильный ответ."
  },
  {
    "id": 121,
    "english": "city",
    "translation": "город",
    "translation_ru": "город",
    "transcription": "/ˈsɪti/",
    "level": "A1",
    "topic": "travel",
    "part_of_speech": "noun",
    "example_en": "This city is beautiful.",
    "example_ru": "Этот город красивый."
  },
  {
    "id": 122,
    "english": "village",
    "translation": "деревня",
    "translation_ru": "деревня",
    "transcription": "/ˈvɪlɪdʒ/",
    "level": "A1",
    "topic": "travel",
    "part_of_speech": "noun",
    "example_en": "My grandparents live in a village.",
    "example_ru": "Мои бабушка и дедушка живут в деревне."
  },
  {
    "id": 123,
    "english": "country",
    "translation": "страна",
    "translation_ru": "страна",
    "transcription": "/ˈkʌntri/",
    "level": "A1",
    "topic": "travel",
    "part_of_speech": "noun",
    "example_en": "France is a country in Europe.",
    "example_ru": "Франция — страна в Европе."
  },
  {
    "id": 124,
    "english": "street",
    "translation": "улица",
    "translation_ru": "улица",
    "transcription": "/striːt/",
    "level": "A1",
    "topic": "travel",
    "part_of_speech": "noun",
    "example_en": "This street is very busy.",
    "example_ru": "Эта улица очень оживлённая."
  },
  {
    "id": 125,
    "english": "road",
    "translation": "дорога",
    "translation_ru": "дорога",
    "transcription": "/rəʊd/",
    "level": "A1",
    "topic": "travel",
    "part_of_speech": "noun",
    "example_en": "The road is long.",
    "example_ru": "Дорога длинная."
  },
  {
    "id": 126,
    "english": "station",
    "translation": "станция",
    "translation_ru": "станция",
    "transcription": "/ˈsteɪʃn/",
    "level": "A1",
    "topic": "travel",
    "part_of_speech": "noun",
    "example_en": "The station is near the hotel.",
    "example_ru": "Станция рядом с отелем."
  },
  {
    "id": 127,
    "english": "airport",
    "translation": "аэропорт",
    "translation_ru": "аэропорт",
    "transcription": "/ˈeəpɔːt/",
    "level": "A1",
    "topic": "travel",
    "part_of_speech": "noun",
    "example_en": "We arrived at the airport early.",
    "example_ru": "Мы приехали в аэропорт рано."
  },
  {
    "id": 128,
    "english": "hotel",
    "translation": "отель",
    "translation_ru": "отель",
    "transcription": "/həʊˈtel/",
    "level": "A1",
    "topic": "travel",
    "part_of_speech": "noun",
    "example_en": "The hotel is clean.",
    "example_ru": "Отель чистый."
  },
  {
    "id": 129,
    "english": "ticket",
    "translation": "билет",
    "translation_ru": "билет",
    "transcription": "/ˈtɪkɪt/",
    "level": "A1",
    "topic": "travel",
    "part_of_speech": "noun",
    "example_en": "I bought a train ticket.",
    "example_ru": "Я купил билет на поезд."
  },
  {
    "id": 130,
    "english": "passport",
    "translation": "паспорт",
    "translation_ru": "паспорт",
    "transcription": "/ˈpɑːspɔːt/",
    "level": "A1",
    "topic": "travel",
    "part_of_speech": "noun",
    "example_en": "Don't forget your passport.",
    "example_ru": "Не забудь паспорт."
  },
  {
    "id": 131,
    "english": "luggage",
    "translation": "багаж",
    "translation_ru": "багаж",
    "transcription": "/ˈlʌɡɪdʒ/",
    "level": "A2",
    "topic": "travel",
    "part_of_speech": "noun",
    "example_en": "My luggage is heavy.",
    "example_ru": "Мой багаж тяжёлый."
  },
  {
    "id": 132,
    "english": "map",
    "translation": "карта",
    "translation_ru": "карта",
    "transcription": "/mæp/",
    "level": "A1",
    "topic": "travel",
    "part_of_speech": "noun",
    "example_en": "We need a map.",
    "example_ru": "Нам нужна карта."
  },
  {
    "id": 133,
    "english": "bus",
    "translation": "автобус",
    "translation_ru": "автобус",
    "transcription": "/bʌs/",
    "level": "A1",
    "topic": "travel",
    "part_of_speech": "noun",
    "example_en": "The bus is late.",
    "example_ru": "Автобус опаздывает."
  },
  {
    "id": 134,
    "english": "train",
    "translation": "поезд",
    "translation_ru": "поезд",
    "transcription": "/treɪn/",
    "level": "A1",
    "topic": "travel",
    "part_of_speech": "noun",
    "example_en": "The train leaves at eight.",
    "example_ru": "Поезд отправляется в восемь."
  },
  {
    "id": 135,
    "english": "plane",
    "translation": "самолёт",
    "translation_ru": "самолёт",
    "transcription": "/pleɪn/",
    "level": "A1",
    "topic": "travel",
    "part_of_speech": "noun",
    "example_en": "The plane is ready to leave.",
    "example_ru": "Самолёт готов к вылету."
  },
  {
    "id": 136,
    "english": "car",
    "translation": "машина",
    "translation_ru": "машина",
    "transcription": "/kɑːr/",
    "level": "A1",
    "topic": "travel",
    "part_of_speech": "noun",
    "example_en": "My car is outside.",
    "example_ru": "Моя машина снаружи."
  },
  {
    "id": 137,
    "english": "bicycle",
    "translation": "велосипед",
    "translation_ru": "велосипед",
    "transcription": "/ˈbaɪsɪkl/",
    "level": "A1",
    "topic": "travel",
    "part_of_speech": "noun",
    "example_en": "He rides a bicycle to work.",
    "example_ru": "Он ездит на работу на велосипеде."
  },
  {
    "id": 138,
    "english": "journey",
    "translation": "поездка",
    "translation_ru": "поездка",
    "transcription": "/ˈdʒɜːni/",
    "level": "A2",
    "topic": "travel",
    "part_of_speech": "noun",
    "example_en": "The journey took three hours.",
    "example_ru": "Поездка заняла три часа."
  },
  {
    "id": 139,
    "english": "trip",
    "translation": "поездка",
    "translation_ru": "поездка",
    "transcription": "/trɪp/",
    "level": "A1",
    "topic": "travel",
    "part_of_speech": "noun",
    "example_en": "We had a short trip to the sea.",
    "example_ru": "У нас была короткая поездка к морю."
  },
  {
    "id": 140,
    "english": "holiday",
    "translation": "отпуск",
    "translation_ru": "отпуск",
    "transcription": "/ˈhɒlədeɪ/",
    "level": "A1",
    "topic": "travel",
    "part_of_speech": "noun",
    "example_en": "I need a holiday.",
    "example_ru": "Мне нужен отпуск."
  },
  {
    "id": 141,
    "english": "school",
    "translation": "школа",
    "translation_ru": "школа",
    "transcription": "/skuːl/",
    "level": "A1",
    "topic": "school and work",
    "part_of_speech": "noun",
    "example_en": "My son goes to school.",
    "example_ru": "Мой сын ходит в школу."
  },
  {
    "id": 142,
    "english": "university",
    "translation": "университет",
    "translation_ru": "университет",
    "transcription": "/ˌjuːnɪˈvɜːsəti/",
    "level": "A1",
    "topic": "school and work",
    "part_of_speech": "noun",
    "example_en": "She studies at university.",
    "example_ru": "Она учится в университете."
  },
  {
    "id": 143,
    "english": "teacher",
    "translation": "учитель",
    "translation_ru": "учитель",
    "transcription": "/ˈtiːtʃər/",
    "level": "A1",
    "topic": "school and work",
    "part_of_speech": "noun",
    "example_en": "The teacher is in the classroom.",
    "example_ru": "Учитель в классе."
  },
  {
    "id": 144,
    "english": "student",
    "translation": "студент",
    "translation_ru": "студент",
    "transcription": "/ˈstjuːdənt/",
    "level": "A1",
    "topic": "school and work",
    "part_of_speech": "noun",
    "example_en": "He is a good student.",
    "example_ru": "Он хороший студент."
  },
  {
    "id": 145,
    "english": "lesson",
    "translation": "урок",
    "translation_ru": "урок",
    "transcription": "/ˈlesn/",
    "level": "A1",
    "topic": "school and work",
    "part_of_speech": "noun",
    "example_en": "The lesson starts at ten.",
    "example_ru": "Урок начинается в десять."
  },
  {
    "id": 146,
    "english": "homework",
    "translation": "домашнее задание",
    "translation_ru": "домашнее задание",
    "transcription": "/ˈhəʊmwɜːk/",
    "level": "A1",
    "topic": "school and work",
    "part_of_speech": "noun",
    "example_en": "I did my homework.",
    "example_ru": "Я сделал домашнее задание."
  },
  {
    "id": 147,
    "english": "exam",
    "translation": "экзамен",
    "translation_ru": "экзамен",
    "transcription": "/ɪɡˈzæm/",
    "level": "A1",
    "topic": "school and work",
    "part_of_speech": "noun",
    "example_en": "The exam was difficult.",
    "example_ru": "Экзамен был сложным."
  },
  {
    "id": 148,
    "english": "question",
    "translation": "вопрос",
    "translation_ru": "вопрос",
    "transcription": "/ˈkwestʃən/",
    "level": "A1",
    "topic": "school and work",
    "part_of_speech": "noun",
    "example_en": "I have a question.",
    "example_ru": "У меня есть вопрос."
  },
  {
    "id": 149,
    "english": "reply",
    "translation": "отвечать",
    "translation_ru": "отвечать",
    "transcription": "/rɪˈplaɪ/",
    "level": "A1",
    "topic": "daily verbs",
    "part_of_speech": "verb",
    "example_en": "Please reply to my message.",
    "example_ru": "Пожалуйста, ответь на моё сообщение."
  },
  {
    "id": 150,
    "english": "book",
    "translation": "книга",
    "translation_ru": "книга",
    "transcription": "/bʊk/",
    "level": "A1",
    "topic": "school and work",
    "part_of_speech": "noun",
    "example_en": "This book is interesting.",
    "example_ru": "Эта книга интересная."
  },
  {
    "id": 151,
    "english": "notebook",
    "translation": "тетрадь",
    "translation_ru": "тетрадь",
    "transcription": "/ˈnəʊtbʊk/",
    "level": "A1",
    "topic": "school and work",
    "part_of_speech": "noun",
    "example_en": "Write it in your notebook.",
    "example_ru": "Запиши это в тетрадь."
  },
  {
    "id": 152,
    "english": "pen",
    "translation": "ручка",
    "translation_ru": "ручка",
    "transcription": "/pen/",
    "level": "A1",
    "topic": "school and work",
    "part_of_speech": "noun",
    "example_en": "Can I borrow your pen?",
    "example_ru": "Можно взять твою ручку?"
  },
  {
    "id": 153,
    "english": "pencil",
    "translation": "карандаш",
    "translation_ru": "карандаш",
    "transcription": "/ˈpensl/",
    "level": "A1",
    "topic": "school and work",
    "part_of_speech": "noun",
    "example_en": "Use a pencil for this exercise.",
    "example_ru": "Используй карандаш для этого упражнения."
  },
  {
    "id": 154,
    "english": "office",
    "translation": "офис",
    "translation_ru": "офис",
    "transcription": "/ˈɒfɪs/",
    "level": "A1",
    "topic": "school and work",
    "part_of_speech": "noun",
    "example_en": "She works in an office.",
    "example_ru": "Она работает в офисе."
  },
  {
    "id": 155,
    "english": "job",
    "translation": "работа",
    "translation_ru": "работа",
    "transcription": "/dʒɒb/",
    "level": "A1",
    "topic": "school and work",
    "part_of_speech": "noun",
    "example_en": "He found a new job.",
    "example_ru": "Он нашёл новую работу."
  },
  {
    "id": 156,
    "english": "work",
    "translation": "работать",
    "translation_ru": "работать",
    "transcription": "/wɜːk/",
    "level": "A1",
    "topic": "school and work",
    "part_of_speech": "verb",
    "example_en": "I work from Monday to Friday.",
    "example_ru": "Я работаю с понедельника по пятницу."
  },
  {
    "id": 157,
    "english": "study",
    "translation": "учиться",
    "translation_ru": "учиться",
    "transcription": "/ˈstʌdi/",
    "level": "A1",
    "topic": "school and work",
    "part_of_speech": "verb",
    "example_en": "I study English every day.",
    "example_ru": "Я учу английский каждый день."
  },
  {
    "id": 158,
    "english": "learn",
    "translation": "изучать",
    "translation_ru": "изучать",
    "transcription": "/lɜːn/",
    "level": "A1",
    "topic": "school and work",
    "part_of_speech": "verb",
    "example_en": "We learn new words.",
    "example_ru": "Мы учим новые слова."
  },
  {
    "id": 159,
    "english": "write",
    "translation": "писать",
    "translation_ru": "писать",
    "transcription": "/raɪt/",
    "level": "A1",
    "topic": "school and work",
    "part_of_speech": "verb",
    "example_en": "Write your name here.",
    "example_ru": "Напиши своё имя здесь."
  },
  {
    "id": 160,
    "english": "read",
    "translation": "читать",
    "translation_ru": "читать",
    "transcription": "/riːd/",
    "level": "A1",
    "topic": "school and work",
    "part_of_speech": "verb",
    "example_en": "I read before bed.",
    "example_ru": "Я читаю перед сном."
  },
  {
    "id": 161,
    "english": "head",
    "translation": "голова",
    "translation_ru": "голова",
    "transcription": "/hed/",
    "level": "A1",
    "topic": "body and health",
    "part_of_speech": "noun",
    "example_en": "My head hurts.",
    "example_ru": "У меня болит голова."
  },
  {
    "id": 162,
    "english": "face",
    "translation": "лицо",
    "translation_ru": "лицо",
    "transcription": "/feɪs/",
    "level": "A1",
    "topic": "body and health",
    "part_of_speech": "noun",
    "example_en": "Wash your face.",
    "example_ru": "Умой лицо."
  },
  {
    "id": 163,
    "english": "eye",
    "translation": "глаз",
    "translation_ru": "глаз",
    "transcription": "/aɪ/",
    "level": "A1",
    "topic": "body and health",
    "part_of_speech": "noun",
    "example_en": "She has blue eyes.",
    "example_ru": "У неё голубые глаза."
  },
  {
    "id": 164,
    "english": "ear",
    "translation": "ухо",
    "translation_ru": "ухо",
    "transcription": "/ɪər/",
    "level": "A1",
    "topic": "body and health",
    "part_of_speech": "noun",
    "example_en": "My ear hurts.",
    "example_ru": "У меня болит ухо."
  },
  {
    "id": 165,
    "english": "nose",
    "translation": "нос",
    "translation_ru": "нос",
    "transcription": "/nəʊz/",
    "level": "A1",
    "topic": "body and health",
    "part_of_speech": "noun",
    "example_en": "His nose is cold.",
    "example_ru": "У него холодный нос."
  },
  {
    "id": 166,
    "english": "mouth",
    "translation": "рот",
    "translation_ru": "рот",
    "transcription": "/maʊθ/",
    "level": "A1",
    "topic": "body and health",
    "part_of_speech": "noun",
    "example_en": "Open your mouth.",
    "example_ru": "Открой рот."
  },
  {
    "id": 167,
    "english": "tooth",
    "translation": "зуб",
    "translation_ru": "зуб",
    "transcription": "/tuːθ/",
    "level": "A1",
    "topic": "body and health",
    "part_of_speech": "noun",
    "example_en": "My tooth hurts.",
    "example_ru": "У меня болит зуб."
  },
  {
    "id": 168,
    "english": "hand",
    "translation": "рука",
    "translation_ru": "рука",
    "transcription": "/hænd/",
    "level": "A1",
    "topic": "body and health",
    "part_of_speech": "noun",
    "example_en": "Wash your hands.",
    "example_ru": "Вымой руки."
  },
  {
    "id": 169,
    "english": "arm",
    "translation": "рука",
    "translation_ru": "рука",
    "transcription": "/ɑːm/",
    "level": "A1",
    "topic": "body and health",
    "part_of_speech": "noun",
    "example_en": "He broke his arm.",
    "example_ru": "Он сломал руку."
  },
  {
    "id": 170,
    "english": "leg",
    "translation": "нога",
    "translation_ru": "нога",
    "transcription": "/leɡ/",
    "level": "A1",
    "topic": "body and health",
    "part_of_speech": "noun",
    "example_en": "My leg hurts.",
    "example_ru": "У меня болит нога."
  },
  {
    "id": 171,
    "english": "foot",
    "translation": "ступня",
    "translation_ru": "ступня",
    "transcription": "/fʊt/",
    "level": "A1",
    "topic": "body and health",
    "part_of_speech": "noun",
    "example_en": "My foot is cold.",
    "example_ru": "У меня замёрзла ступня."
  },
  {
    "id": 172,
    "english": "back",
    "translation": "спина",
    "translation_ru": "спина",
    "transcription": "/bæk/",
    "level": "A1",
    "topic": "body and health",
    "part_of_speech": "noun",
    "example_en": "My back hurts.",
    "example_ru": "У меня болит спина."
  },
  {
    "id": 173,
    "english": "heart",
    "translation": "сердце",
    "translation_ru": "сердце",
    "transcription": "/hɑːt/",
    "level": "A1",
    "topic": "body and health",
    "part_of_speech": "noun",
    "example_en": "The heart is an important organ.",
    "example_ru": "Сердце — важный орган."
  },
  {
    "id": 174,
    "english": "blood",
    "translation": "кровь",
    "translation_ru": "кровь",
    "transcription": "/blʌd/",
    "level": "A2",
    "topic": "body and health",
    "part_of_speech": "noun",
    "example_en": "The doctor took some blood.",
    "example_ru": "Врач взял немного крови."
  },
  {
    "id": 175,
    "english": "doctor",
    "translation": "врач",
    "translation_ru": "врач",
    "transcription": "/ˈdɒktər/",
    "level": "A1",
    "topic": "body and health",
    "part_of_speech": "noun",
    "example_en": "You should see a doctor.",
    "example_ru": "Тебе стоит обратиться к врачу."
  },
  {
    "id": 176,
    "english": "nurse",
    "translation": "медсестра",
    "translation_ru": "медсестра",
    "transcription": "/nɜːs/",
    "level": "A1",
    "topic": "body and health",
    "part_of_speech": "noun",
    "example_en": "The nurse helped me.",
    "example_ru": "Медсестра помогла мне."
  },
  {
    "id": 177,
    "english": "medicine",
    "translation": "лекарство",
    "translation_ru": "лекарство",
    "transcription": "/ˈmedsən/",
    "level": "A1",
    "topic": "body and health",
    "part_of_speech": "noun",
    "example_en": "Take this medicine twice a day.",
    "example_ru": "Принимай это лекарство два раза в день."
  },
  {
    "id": 178,
    "english": "hospital",
    "translation": "больница",
    "translation_ru": "больница",
    "transcription": "/ˈhɒspɪtl/",
    "level": "A1",
    "topic": "body and health",
    "part_of_speech": "noun",
    "example_en": "He is in hospital.",
    "example_ru": "Он в больнице."
  },
  {
    "id": 179,
    "english": "pain",
    "translation": "боль",
    "translation_ru": "боль",
    "transcription": "/peɪn/",
    "level": "A2",
    "topic": "body and health",
    "part_of_speech": "noun",
    "example_en": "I have pain in my back.",
    "example_ru": "У меня боль в спине."
  },
  {
    "id": 180,
    "english": "ill",
    "translation": "больной",
    "translation_ru": "больной",
    "transcription": "/ɪl/",
    "level": "A1",
    "topic": "body and health",
    "part_of_speech": "adjective",
    "example_en": "She is ill today.",
    "example_ru": "Она сегодня больна."
  },
  {
    "id": 181,
    "english": "world",
    "translation": "мир",
    "translation_ru": "мир",
    "transcription": "/wɜːld/",
    "level": "A1",
    "topic": "places and nature",
    "part_of_speech": "noun",
    "example_en": "The world is changing.",
    "example_ru": "Мир меняется."
  },
  {
    "id": 182,
    "english": "countryside",
    "translation": "сельская местность",
    "translation_ru": "сельская местность",
    "transcription": "/ˈkʌntrisaɪd/",
    "level": "A2",
    "topic": "places and nature",
    "part_of_speech": "noun",
    "example_en": "They live in the countryside.",
    "example_ru": "Они живут в сельской местности."
  },
  {
    "id": 183,
    "english": "sea",
    "translation": "море",
    "translation_ru": "море",
    "transcription": "/siː/",
    "level": "A1",
    "topic": "places and nature",
    "part_of_speech": "noun",
    "example_en": "The sea is calm today.",
    "example_ru": "Море сегодня спокойное."
  },
  {
    "id": 184,
    "english": "river",
    "translation": "река",
    "translation_ru": "река",
    "transcription": "/ˈrɪvər/",
    "level": "A1",
    "topic": "places and nature",
    "part_of_speech": "noun",
    "example_en": "The river is deep.",
    "example_ru": "Река глубокая."
  },
  {
    "id": 185,
    "english": "lake",
    "translation": "озеро",
    "translation_ru": "озеро",
    "transcription": "/leɪk/",
    "level": "A1",
    "topic": "places and nature",
    "part_of_speech": "noun",
    "example_en": "There is a lake near the village.",
    "example_ru": "Рядом с деревней есть озеро."
  },
  {
    "id": 186,
    "english": "mountain",
    "translation": "гора",
    "translation_ru": "гора",
    "transcription": "/ˈmaʊntən/",
    "level": "A1",
    "topic": "places and nature",
    "part_of_speech": "noun",
    "example_en": "The mountain is high.",
    "example_ru": "Гора высокая."
  },
  {
    "id": 187,
    "english": "forest",
    "translation": "лес",
    "translation_ru": "лес",
    "transcription": "/ˈfɒrɪst/",
    "level": "A1",
    "topic": "places and nature",
    "part_of_speech": "noun",
    "example_en": "We walked through the forest.",
    "example_ru": "Мы шли через лес."
  },
  {
    "id": 188,
    "english": "field",
    "translation": "поле",
    "translation_ru": "поле",
    "transcription": "/fiːld/",
    "level": "A1",
    "topic": "places and nature",
    "part_of_speech": "noun",
    "example_en": "Cows are in the field.",
    "example_ru": "Коровы в поле."
  },
  {
    "id": 189,
    "english": "tree",
    "translation": "дерево",
    "translation_ru": "дерево",
    "transcription": "/triː/",
    "level": "A1",
    "topic": "places and nature",
    "part_of_speech": "noun",
    "example_en": "The tree is very old.",
    "example_ru": "Дерево очень старое."
  },
  {
    "id": 190,
    "english": "flower",
    "translation": "цветок",
    "translation_ru": "цветок",
    "transcription": "/ˈflaʊər/",
    "level": "A1",
    "topic": "places and nature",
    "part_of_speech": "noun",
    "example_en": "This flower smells nice.",
    "example_ru": "Этот цветок приятно пахнет."
  },
  {
    "id": 191,
    "english": "sky",
    "translation": "небо",
    "translation_ru": "небо",
    "transcription": "/skaɪ/",
    "level": "A1",
    "topic": "places and nature",
    "part_of_speech": "noun",
    "example_en": "The sky is blue.",
    "example_ru": "Небо голубое."
  },
  {
    "id": 192,
    "english": "sun",
    "translation": "солнце",
    "translation_ru": "солнце",
    "transcription": "/sʌn/",
    "level": "A1",
    "topic": "places and nature",
    "part_of_speech": "noun",
    "example_en": "The sun is shining.",
    "example_ru": "Солнце светит."
  },
  {
    "id": 193,
    "english": "moon",
    "translation": "луна",
    "translation_ru": "луна",
    "transcription": "/muːn/",
    "level": "A1",
    "topic": "places and nature",
    "part_of_speech": "noun",
    "example_en": "The moon is bright tonight.",
    "example_ru": "Луна сегодня яркая."
  },
  {
    "id": 194,
    "english": "star",
    "translation": "звезда",
    "translation_ru": "звезда",
    "transcription": "/stɑːr/",
    "level": "A1",
    "topic": "places and nature",
    "part_of_speech": "noun",
    "example_en": "I can see a star.",
    "example_ru": "Я вижу звезду."
  },
  {
    "id": 195,
    "english": "rain",
    "translation": "дождь",
    "translation_ru": "дождь",
    "transcription": "/reɪn/",
    "level": "A1",
    "topic": "places and nature",
    "part_of_speech": "noun",
    "example_en": "The rain is heavy.",
    "example_ru": "Дождь сильный."
  },
  {
    "id": 196,
    "english": "snow",
    "translation": "снег",
    "translation_ru": "снег",
    "transcription": "/snəʊ/",
    "level": "A1",
    "topic": "places and nature",
    "part_of_speech": "noun",
    "example_en": "Snow is falling.",
    "example_ru": "Идёт снег."
  },
  {
    "id": 197,
    "english": "wind",
    "translation": "ветер",
    "translation_ru": "ветер",
    "transcription": "/wɪnd/",
    "level": "A1",
    "topic": "places and nature",
    "part_of_speech": "noun",
    "example_en": "The wind is strong.",
    "example_ru": "Ветер сильный."
  },
  {
    "id": 198,
    "english": "weather",
    "translation": "погода",
    "translation_ru": "погода",
    "transcription": "/ˈweðər/",
    "level": "A1",
    "topic": "places and nature",
    "part_of_speech": "noun",
    "example_en": "The weather is good today.",
    "example_ru": "Погода сегодня хорошая."
  },
  {
    "id": 199,
    "english": "fire",
    "translation": "огонь",
    "translation_ru": "огонь",
    "transcription": "/ˈfaɪər/",
    "level": "A1",
    "topic": "places and nature",
    "part_of_speech": "noun",
    "example_en": "The fire is warm.",
    "example_ru": "Огонь тёплый."
  },
  {
    "id": 200,
    "english": "earth",
    "translation": "земля",
    "translation_ru": "земля",
    "transcription": "/ɜːθ/",
    "level": "A2",
    "topic": "places and nature",
    "part_of_speech": "noun",
    "example_en": "The earth was wet after the rain.",
    "example_ru": "Земля была мокрой после дождя."
  }
]